doclayout_yolo/__init__.py
doclayout_yolo/assets/bus.jpg
doclayout_yolo/assets/zidane.jpg
doclayout_yolo/cfg/__init__.py
doclayout_yolo/cfg/default.yaml
doclayout_yolo/cfg/datasets/d4la.yaml
doclayout_yolo/cfg/datasets/doclaynet.yaml
doclayout_yolo/cfg/models/rt-detr/rtdetr-l.yaml
doclayout_yolo/cfg/models/rt-detr/rtdetr-resnet101.yaml
doclayout_yolo/cfg/models/rt-detr/rtdetr-resnet50.yaml
doclayout_yolo/cfg/models/rt-detr/rtdetr-x.yaml
doclayout_yolo/cfg/models/v10/yolov10b.yaml
doclayout_yolo/cfg/models/v10/yolov10l.yaml
doclayout_yolo/cfg/models/v10/yolov10m-doclayout.yaml
doclayout_yolo/cfg/models/v10/yolov10m.yaml
doclayout_yolo/cfg/models/v10/yolov10n.yaml
doclayout_yolo/cfg/models/v10/yolov10s.yaml
doclayout_yolo/cfg/models/v10/yolov10x.yaml
doclayout_yolo/cfg/models/v3/yolov3-spp.yaml
doclayout_yolo/cfg/models/v3/yolov3-tiny.yaml
doclayout_yolo/cfg/models/v3/yolov3.yaml
doclayout_yolo/cfg/models/v5/yolov5-p6.yaml
doclayout_yolo/cfg/models/v5/yolov5.yaml
doclayout_yolo/cfg/models/v6/yolov6.yaml
doclayout_yolo/cfg/models/v8/yolov8-cls-resnet101.yaml
doclayout_yolo/cfg/models/v8/yolov8-cls-resnet50.yaml
doclayout_yolo/cfg/models/v8/yolov8-cls.yaml
doclayout_yolo/cfg/models/v8/yolov8-ghost-p2.yaml
doclayout_yolo/cfg/models/v8/yolov8-ghost-p6.yaml
doclayout_yolo/cfg/models/v8/yolov8-ghost.yaml
doclayout_yolo/cfg/models/v8/yolov8-obb.yaml
doclayout_yolo/cfg/models/v8/yolov8-p2.yaml
doclayout_yolo/cfg/models/v8/yolov8-p6.yaml
doclayout_yolo/cfg/models/v8/yolov8-pose-p6.yaml
doclayout_yolo/cfg/models/v8/yolov8-pose.yaml
doclayout_yolo/cfg/models/v8/yolov8-rtdetr.yaml
doclayout_yolo/cfg/models/v8/yolov8-seg-p6.yaml
doclayout_yolo/cfg/models/v8/yolov8-seg.yaml
doclayout_yolo/cfg/models/v8/yolov8-world.yaml
doclayout_yolo/cfg/models/v8/yolov8-worldv2.yaml
doclayout_yolo/cfg/models/v8/yolov8.yaml
doclayout_yolo/cfg/models/v9/yolov9c.yaml
doclayout_yolo/cfg/models/v9/yolov9e.yaml
doclayout_yolo/cfg/trackers/botsort.yaml
doclayout_yolo/cfg/trackers/bytetrack.yaml
doclayout_yolo-0.0.2.dist-info/LICENSE
doclayout_yolo-0.0.2.dist-info/METADATA
doclayout_yolo-0.0.2.dist-info/WHEEL
doclayout_yolo-0.0.2.dist-info/entry_points.txt
doclayout_yolo-0.0.2.dist-info/top_level.txt
doclayout_yolo-0.0.2.dist-info/RECORD
