Metadata-Version: 2.1
Name: doclayout_yolo
Version: 0.0.2
Summary: DocLayout-YOLO: an effecient and robust document layout analysis method.
Author: Zhiyuan Zhao, Hengrui Kang, Bin Wang, Conghui He
Maintainer: Zhiyuan Zhao, Bin Wang
License: AGPL-3.0
Keywords: Document Layout Analysis,YOLO
Classifier: Development Status :: 4 - Beta
Classifier: Intended Audience :: Developers
Classifier: Intended Audience :: Education
Classifier: Intended Audience :: Science/Research
Classifier: License :: OSI Approved :: GNU Affero General Public License v3 or later (AGPLv3+)
Classifier: Programming Language :: Python :: 3
Classifier: Programming Language :: Python :: 3.8
Classifier: Programming Language :: Python :: 3.9
Classifier: Programming Language :: Python :: 3.10
Classifier: Programming Language :: Python :: 3.11
Classifier: Programming Language :: Python :: 3.12
Classifier: Topic :: Software Development
Classifier: Topic :: Scientific/Engineering
Classifier: Topic :: Scientific/Engineering :: Artificial Intelligence
Classifier: Topic :: Scientific/Engineering :: Image Recognition
Classifier: Operating System :: POSIX :: Linux
Classifier: Operating System :: MacOS
Classifier: Operating System :: Microsoft :: Windows
Requires-Python: >=3.8
License-File: LICENSE
Requires-Dist: matplotlib>=3.3.0
Requires-Dist: opencv-python>=4.6.0
Requires-Dist: pillow>=7.1.2
Requires-Dist: pyyaml>=5.3.1
Requires-Dist: requests>=2.23.0
Requires-Dist: scipy>=1.4.1
Requires-Dist: torch>=2.0.1
Requires-Dist: torchvision>=0.15.2
Requires-Dist: tqdm>=4.64.0
Requires-Dist: psutil
Requires-Dist: py-cpuinfo
Requires-Dist: thop>=0.1.1
Requires-Dist: pandas>=1.1.4
Requires-Dist: seaborn>=0.11.0
Requires-Dist: albumentations>=1.4.11
Provides-Extra: dev
Requires-Dist: ipython; extra == "dev"
Requires-Dist: check-manifest; extra == "dev"
Requires-Dist: pre-commit; extra == "dev"
Requires-Dist: pytest; extra == "dev"
Requires-Dist: pytest-cov; extra == "dev"
Requires-Dist: coverage[toml]; extra == "dev"
Requires-Dist: mkdocs-material>=9.5.9; extra == "dev"
Requires-Dist: mkdocstrings[python]; extra == "dev"
Requires-Dist: mkdocs-jupyter; extra == "dev"
Requires-Dist: mkdocs-redirects; extra == "dev"
Requires-Dist: mkdocs-ultralytics-plugin>=0.0.44; extra == "dev"
Provides-Extra: explorer
Requires-Dist: lancedb; extra == "explorer"
Requires-Dist: duckdb<=0.9.2; extra == "explorer"
Requires-Dist: streamlit; extra == "explorer"
Provides-Extra: export
Requires-Dist: onnx>=1.12.0; extra == "export"
Requires-Dist: openvino>=2024.0.0; extra == "export"
Requires-Dist: coremltools>=7.0; (platform_system != "Windows" and python_version <= "3.11") and extra == "export"
Requires-Dist: tensorflow<=2.13.1; python_version <= "3.11" and extra == "export"
Requires-Dist: tensorflowjs>=3.9.0; python_version <= "3.11" and extra == "export"
Provides-Extra: extra
Requires-Dist: hub-sdk>=0.0.5; extra == "extra"
Requires-Dist: ipython; extra == "extra"
Requires-Dist: albumentations>=1.0.3; extra == "extra"
Requires-Dist: pycocotools>=2.0.7; extra == "extra"
Provides-Extra: logging
Requires-Dist: comet; extra == "logging"
Requires-Dist: tensorboard>=2.13.0; extra == "logging"
Requires-Dist: dvclive>=2.12.0; extra == "logging"
